sinethesizer/__init__.py
sinethesizer/__main__.py
sinethesizer/default_config.yml
sinethesizer/effects/__init__.py
sinethesizer/effects/amplitude.py
sinethesizer/effects/automation.py
sinethesizer/effects/chorus.py
sinethesizer/effects/equalizer.py
sinethesizer/effects/filter.py
sinethesizer/effects/filter_sweep.py
sinethesizer/effects/overdrive.py
sinethesizer/effects/registry.py
sinethesizer/effects/reverb.py
sinethesizer/effects/stereo.py
sinethesizer/effects/tremolo.py
sinethesizer/effects/vibrato.py
sinethesizer/envelopes/__init__.py
sinethesizer/envelopes/ahdsr.py
sinethesizer/envelopes/misc.py
sinethesizer/envelopes/registry.py
sinethesizer/envelopes/user_defined.py
sinethesizer/io/__init__.py
sinethesizer/io/events_to_wav.py
sinethesizer/io/load_presets.py
sinethesizer/io/midi_to_events.py
sinethesizer/io/tsv_to_events.py
sinethesizer/oscillators/__init__.py
sinethesizer/oscillators/analog.py
sinethesizer/oscillators/facade.py
sinethesizer/oscillators/karplus_strong.py
sinethesizer/oscillators/noise.py
sinethesizer/synth/__init__.py
sinethesizer/synth/core.py
sinethesizer/synth/event_to_amplitude_factor.py
sinethesizer/utils/__init__.py
sinethesizer/utils/misc.py
sinethesizer/utils/music_theory.py
sinethesizer-0.6.2.dist-info/LICENSE
sinethesizer-0.6.2.dist-info/METADATA
sinethesizer-0.6.2.dist-info/WHEEL
sinethesizer-0.6.2.dist-info/top_level.txt
sinethesizer-0.6.2.dist-info/RECORD
