Metadata-Version: 2.1
Name: sinethesizer
Version: 0.6.2
Summary: A standalone synthesizer that is controlled through text files in an extendable way
Author-email: Nikolay Lysenko <nikolay-lysenco@yandex.ru>
Project-URL: Homepage, https://github.com/Nikolay-Lysenko/sinethesizer
Keywords: additive_synthesis,adsr_envelope,ahdsr,filter_envelope,modulation_index,pm_synthesis,reverb,sound_effects,subtractive_synthesis,synthesizer
Classifier: Development Status :: 4 - Beta
Classifier: Intended Audience :: End Users/Desktop
Classifier: Topic :: Artistic Software
Classifier: Topic :: Multimedia :: Sound/Audio :: Sound Synthesis
Classifier: License :: OSI Approved :: MIT License
Classifier: Programming Language :: Python :: 3
Requires-Python: >=3.9
License-File: LICENSE
Requires-Dist: numpy
Requires-Dist: pretty-midi
Requires-Dist: PyYAML
Requires-Dist: scipy
